__init__.py
myfunctions.py
test_myfunctions.py
cr_nlp.egg-info/PKG-INFO
cr_nlp.egg-info/SOURCES.txt
cr_nlp.egg-info/dependency_links.txt
cr_nlp.egg-info/requires.txt
cr_nlp.egg-info/top_level.txt
cr_nlp-0.1.6.dist-info/METADATA
cr_nlp-0.1.6.dist-info/WHEEL
cr_nlp-0.1.6.dist-info/top_level.txt
cr_nlp-0.1.6.dist-info/RECORD
