Metadata-Version: 2.1
Name: cr_nlp
Version: 0.1.6
Summary: Library for NLP tasks by Aryan Oberoi
Home-page: https://github.com/aryanoberoi/IITD-work/tree/main/library/test_library
Author: Aryan Oberoi
Author-email: aryanoberoi267@gmail.com
License: MIT
Classifier: Intended Audience :: Developers
Classifier: Programming Language :: Python
Classifier: Programming Language :: Python :: 3
Classifier: Programming Language :: Python :: 3.6
Classifier: Programming Language :: Python :: 3.7
Classifier: Programming Language :: Python :: 3.8
Classifier: Programming Language :: Python :: 3.9
Classifier: Operating System :: OS Independent
Requires-Dist: transformers
Requires-Dist: nltk
